numa/__init__.py
numa/info.py
numa/memory.py
numa/schedule.py
numa/utils.py
tests/__init__.py
tests/test.py
py_libnuma-1.2.dist-info/LICENSE
py_libnuma-1.2.dist-info/METADATA
py_libnuma-1.2.dist-info/WHEEL
py_libnuma-1.2.dist-info/top_level.txt
py_libnuma-1.2.dist-info/RECORD
