Metadata-Version: 2.1
Name: py-libnuma
Version: 1.2
Summary: Python3 libnuma ctypes wrapper
Home-page: https://github.com/eedalong/pynuma
Author: Xiulong Yuan, Zhan Lu, Zheng Zeng
Author-email: yuanxl19@mails.tsinghua.edu.cn, lu-z18@mails.tsinghua.edu.cn, zengz17@mails.tsinghua.edu.cn
License: License :: OSI Approved :: MIT License
Platform: Linux
Classifier: Development Status :: 2 - Pre-Alpha
Classifier: Intended Audience :: Developers
Classifier: Intended Audience :: Information Technology
Classifier: Intended Audience :: System Administrators
Classifier: License :: OSI Approved :: MIT License
Classifier: Operating System :: POSIX
Classifier: Operating System :: POSIX :: Linux
Classifier: Programming Language :: Python
